rakopy/__init__.py
rakopy/__version__.py
rakopy/consts.py
rakopy/errors.py
rakopy/hub.py
rakopy/model.py
rakopy-0.0.5.dist-info/METADATA
rakopy-0.0.5.dist-info/WHEEL
rakopy-0.0.5.dist-info/licenses/LICENSE
rakopy-0.0.5.dist-info/RECORD
